nbdocs/__init__.py
nbdocs/__main__.py
nbdocs/cfg_tools.py
nbdocs/clean.py
nbdocs/convert.py
nbdocs/core.py
nbdocs/default_settings.py
nbdocs/process.py
nbdocs/typing.py
nbdocs/version.py
nbdocs/apps/__init__.py
nbdocs/apps/app_nb2md.py
nbdocs/apps/app_nbclean.py
nbdocs/apps/app_nbdocs.py
nbdocs/tests/__init__.py
nbdocs/tests/base.py
nbdocs-0.2.2.dist-info/LICENSE
nbdocs-0.2.2.dist-info/METADATA
nbdocs-0.2.2.dist-info/WHEEL
nbdocs-0.2.2.dist-info/entry_points.txt
nbdocs-0.2.2.dist-info/top_level.txt
nbdocs-0.2.2.dist-info/RECORD
