Metadata-Version: 2.1
Name: nbdocs
Version: 0.2.2
Summary: Docs from jupyter notebooks.
Home-page: https://github.com/ayasyrev/nbdocs
Author: Yasyrev Andrei
Author-email: a.yasyrev@gmail.com
License: apache2
Classifier: Programming Language :: Python :: 3
Classifier: License :: OSI Approved :: Apache Software License
Classifier: Operating System :: OS Independent
Requires-Python: >=3.8
License-File: LICENSE
Provides-Extra: test
